norsourceparser/__init__.py
norsourceparser/frontend.py
norsourceparser/core/__init__.py
norsourceparser/core/config.py
norsourceparser/core/constants.py
norsourceparser/core/models.py
norsourceparser/core/parser.py
norsourceparser/core/rules.py
norsourceparser/core/util.py
norsourceparser/resources/gloss.json
norsourceparser/resources/meanings.json
norsourceparser/resources/noun_inflections.json
norsourceparser/resources/pos.json
norsourceparser/resources/verb_corrlist.json
norsourceparser/resources/verb_lex.json
norsourceparser-1.0.0rc2.dist-info/DESCRIPTION.rst
norsourceparser-1.0.0rc2.dist-info/METADATA
norsourceparser-1.0.0rc2.dist-info/RECORD
norsourceparser-1.0.0rc2.dist-info/WHEEL
norsourceparser-1.0.0rc2.dist-info/entry_points.txt
norsourceparser-1.0.0rc2.dist-info/metadata.json
norsourceparser-1.0.0rc2.dist-info/top_level.txt
