Metadata-Version: 2.0
Name: norsourceparser
Version: 1.0.0rc2
Summary: Simple conversion of Norsource-xml files into tc-xml.
Home-page: https://github.com/tOgg1/norsourceparser
Author: Tormod Haugland
Author-email: tormod.haugland@gmail.com
License: MIT license
Keywords: norsourceparser
Platform: UNKNOWN
Classifier: Development Status :: 2 - Pre-Alpha
Classifier: Intended Audience :: Developers
Classifier: License :: OSI Approved :: MIT License
Classifier: Natural Language :: English
Classifier: Programming Language :: Python :: 2
Classifier: Programming Language :: Python :: 2.7
Classifier: Programming Language :: Python :: 3
Classifier: Programming Language :: Python :: 3.3
Classifier: Programming Language :: Python :: 3.4
Classifier: Programming Language :: Python :: 3.5
Requires-Dist: typecraft-python (>=0.5.0)
